fos/__init__.py
fos/callbacks.py
fos/core.py
fos/metrics.py
fos/utils.py
fos-1.0.0.dist-info/DESCRIPTION.rst
fos-1.0.0.dist-info/METADATA
fos-1.0.0.dist-info/RECORD
fos-1.0.0.dist-info/WHEEL
fos-1.0.0.dist-info/metadata.json
fos-1.0.0.dist-info/top_level.txt
