Metadata-Version: 2.0
Name: fos
Version: 1.0.0
Summary: Deeplearning framework for PyTorch
Home-page: https://github.com/neurallayer/fos
Author: FOS Authors
Author-email: info@neurallayer.com
License: UNKNOWN
Platform: UNKNOWN
Classifier: Programming Language :: Python :: 3.8
Classifier: License :: OSI Approved :: Apache Software License
Classifier: Operating System :: OS Independent
